{
    "DISPLAY": {
      "Size": "6.74-inch",
      "Type": "HD+ IPS LCD",
      "Resolution": "720 x 1600 Pixels",
      "PPI": 260,
      "Aspect Ratio": "20:9",
      "Refresh Rate": "90Hz",
      "Brightness": "560nits max",
      "Notch": true
    },
    "OS": "Android 13 with realme UI T Edition",
    "CHIPSET": "UNISOC Tiger T612",
    "CPU": {
      "Type": "Octa Core",
      "Cores": {
        "Cortex-A75": "2x @ 1.8GHz",
        "Cortex-A55": "6x @ 1.8GHz"
      }
    },
    "GPU": "Mali-G57",
    "RAM": "4 GB",
    "REAR_CAMERA": {
      "Type": "Dual Cameras",
      "Main_Camera": {
        "Resolution": "13MP",
        "Features": ["Autofocus"],
        "Flash": "LED",
        "Video_Recording": "Up to 1080p"
      },
      "Monochrome": true
    },
    "FRONT_CAMERA": {
      "Resolution": "5 Megapixels"
    },
    "STORAGE": "64GB",
    "EXPANSION": "Expandable up to 2TB via microSD",
    "SIM_CARD": "Dual SIM (Nano-SIM)",
    "CELLULAR": "4G LTE, 3G HSPA+, 2G EDGE & GPRS Networks",
    "WI-FI": "Wi-Fi 802.11 b/g/n/ac (dual band)",
    "NFC": false,
    "BLUETOOTH": "Bluetooth 5.0",
    "POSITIONING": "GPS",
    "USB_OTG": true,
    "USB_PORT": "USB Type-C",
    "SOUND": {
      "Audio_Jack": "3.5mm"
    },
    "FM_RADIO": true,
    "BIOMETRICS": "Face Recognition & Fingerprint Sensor (side-mounted)",
    "SENSORS": ["Gyroscope", "Compass", "Ambient Light Sensor", "Proximity Sensor", "Accelerometer"],
    "BATTERY": {
      "Type": "5000 mAh Li-Po",
      "Removable": false,
      "Charging_Rate": "10W"
    },
    "MATERIAL": "Glass front, Plastic back (IP54 dust and splash resistant)",
    "DIMENSIONS": "167.7 x 76.67 x 7.99 mm",
    "WEIGHT": "186 g",
    "COLORS": ["Midnight Black", "Sky Blue"]
  }
  