{
  "display": "6.7-inch FHD+ PLS LCD Display (1080 x 2400 Pixels, 393 ppi) with 20:9 Aspect Ratio, 90Hz Refresh Rate, and notch",
  "os": "Android 13 with One UI",
  "chipset": "Qualcomm Snapdragon 680 (6 nm)",
  "cpu": {
    "description": "Octa Core CPU",
    "cores": {
      "Kryo 265 Gold": "2.4GHz",
      "Kryo 265 Silver": "1.9GHz"
    }
  },
  "gpu": "Adreno 610",
  "ram": "4 GB",
  "rear_camera": {
    "main_camera": "50MP Main Camera (f/1.8 Aperture, Autofocus)",
    "macro": "2MP Macro (f/2.4 Aperture)",
    "depth_sensor": "2MP Depth Sensor",
    "flash": "LED Flash",
    "video_recording": "Up to 1080p@60fps video recording"
  },
  "front_camera": {
    "megapixels": 13,
    "aperture": "f/2.0",
    "flash": "LED Flash",
    "video_recording": "Up to 1080p@60fps video recording"
  },
  "storage": "128GB",
  "expansion": "Expandable up to 1TB via microSD",
  "sim_card": "Dual SIM (Nano-SIM)",
  "cellular": ["4G LTE", "3G HSPA+", "2G EDGE & GPRS Networks"],
  "wifi": "Wi-Fi 802.11 b/g/n/ac (dual band)",
  "nfc": "No",
  "bluetooth": "Bluetooth 5.1",
  "positioning": ["GPS", "GLONASS", "GALILEO", "BeiDou"],
  "usb_otg": "Yes",
  "usb_port": "USB Type-C",
  "sound": "Dolby ATMOS, 3.5mm Audio Jack",
  "fm_radio": "No",
  "biometrics": ["Face Recognition", "Fingerprint Sensor (side-mounted)"],
  "sensors": ["Ambient Light Sensor", "Proximity Sensor", "Accelerometer"],
  "battery": "5000 mAh Li-Po Battery (Non-removable) - 25W Fast Charging",
  "material": "Glass front, Plastic back",
  "dimensions": "168.0 x 77.8 x 8.8 mm",
  "weight": "194 g",
  "colors": ["Black", "Light Green"]
}
